setup.py
kafka/__init__.py
kafka/client.py
kafka/codec.py
kafka/common.py
kafka/conn.py
kafka/consumer.py
kafka/partitioner.py
kafka/producer.py
kafka/protocol.py
kafka/queue.py
kafka/util.py
kafka_quixey.egg-info/PKG-INFO
kafka_quixey.egg-info/SOURCES.txt
kafka_quixey.egg-info/dependency_links.txt
kafka_quixey.egg-info/top_level.txt
test/test_integration.py
test/test_unit.py