Metadata-Version: 1.0
Name: kafka-quixey
Version: 0.9.0-q3
Summary: Pure Python client for Apache Kafka
Home-page: https://github.com/quixey/kafka-python
Author: David Arthur, Jim Lim
Author-email: mumrah@gmail.com, jim@quixey.com
License: Copyright 2012, David Arthur under Apache License, v2.0
Platform: UNKNOWN
